haramss_cmd/__init__.py
haramss_cmd/cmd.py
HaramSs_cmd-0.2.0.dist-info/METADATA
HaramSs_cmd-0.2.0.dist-info/WHEEL
HaramSs_cmd-0.2.0.dist-info/entry_points.txt
HaramSs_cmd-0.2.0.dist-info/top_level.txt
HaramSs_cmd-0.2.0.dist-info/RECORD
